django_lead_capture/IMPLEMENTATION.md
django_lead_capture/README.md
django_lead_capture/__init__.py
django_lead_capture/admin.py
django_lead_capture/apps.py
django_lead_capture/checks.py
django_lead_capture/emails.py
django_lead_capture/forms.py
django_lead_capture/models.py
django_lead_capture/tests.py
django_lead_capture/urls.py
django_lead_capture/utils.py
django_lead_capture/views.py
django_lead_capture/migrations/0001_initial.py
django_lead_capture/migrations/0002_leadcaptureconfiguration.py
django_lead_capture/migrations/__init__.py
django_lead_capture/templates/django_lead_capture/analytics.html
django_lead_capture/templates/django_lead_capture/campaign.html
django_lead_capture/templates/django_lead_capture/edit.html
django_lead_capture/templates/django_lead_capture/list.html
django_lead_capture/templates/django_lead_capture/no_models.html
django_lead_capture/templates/django_lead_capture/preview.html
django_lead_capture/templates/django_lead_capture/thank_you.html
django_lead_capture/templates/django_lead_capture/wizard.html
django_lead_capture/templates/django_lead_capture/emails/welcome.html
django_lead_capture-0.1.0.dist-info/METADATA
django_lead_capture-0.1.0.dist-info/WHEEL
django_lead_capture-0.1.0.dist-info/licenses/LICENSE
django_lead_capture-0.1.0.dist-info/RECORD
