Metadata-Version: 2.4
Name: django-lead-capture
Version: 0.1.0
Summary: AI-powered lead capture and coming soon pages for Django with LiteLLM integration
Project-URL: Homepage, https://github.com/heysamtexas/django-lead-capture
Project-URL: Repository, https://github.com/heysamtexas/django-lead-capture
Project-URL: Issues, https://github.com/heysamtexas/django-lead-capture/issues
Project-URL: Changelog, https://github.com/heysamtexas/django-lead-capture/blob/main/CHANGELOG.md
Author: Directory Platform Team
License: MIT
License-File: LICENSE
Keywords: ai,coming-soon,django,email-verification,landing-page,lead-capture,litellm
Classifier: Development Status :: 4 - Beta
Classifier: Environment :: Web Environment
Classifier: Framework :: Django
Classifier: Framework :: Django :: 4.2
Classifier: Framework :: Django :: 5.0
Classifier: Framework :: Django :: 5.1
Classifier: Intended Audience :: Developers
Classifier: License :: OSI Approved :: MIT License
Classifier: Operating System :: OS Independent
Classifier: Programming Language :: Python
Classifier: Programming Language :: Python :: 3
Classifier: Programming Language :: Python :: 3.12
Classifier: Topic :: Internet :: WWW/HTTP
Classifier: Topic :: Internet :: WWW/HTTP :: Dynamic Content
Classifier: Topic :: Software Development :: Libraries :: Python Modules
Classifier: Typing :: Typed
Requires-Python: >=3.12
Requires-Dist: django-bootstrap5>=24.0
Requires-Dist: django-solo>=2.0
Requires-Dist: django>=4.2
Requires-Dist: litellm>=1.0
Provides-Extra: dev
Requires-Dist: django-stubs>=4.2.0; extra == 'dev'
Requires-Dist: mypy>=1.7.0; extra == 'dev'
Requires-Dist: ruff>=0.1.0; extra == 'dev'
